ts_binder/__init__.py
ts_binder/data_processing.py
ts_binder/model_utils.py
ts_binder/visualize.py
time_series_binder-1.0.4.dist-info/LICENSE.txt
time_series_binder-1.0.4.dist-info/METADATA
time_series_binder-1.0.4.dist-info/WHEEL
time_series_binder-1.0.4.dist-info/top_level.txt
time_series_binder-1.0.4.dist-info/RECORD
