Metadata-Version: 2.1
Name: time-series-binder
Version: 1.0.4
Summary: Time Series Binder is a Python library for time series analysis and forecasting. It offers a comprehensive set of tools and models, including Pandas integration, statistical methods, neural networks with Keras, and the NeuralProphet library. With Time Series Binder, you can easily manipulate, visualize, and predict time series data, making it an essential toolkit for researchers and analysts.
Home-page: https://github.com/JhunBrian/time_series_binder
Author: Jhun Brian Andam
Author-email: brianandam123@gmail.com
License: MIT
Keywords: Time Series Analysis,Forecasting
Platform: UNKNOWN
Classifier: Development Status :: 1 - Planning
Classifier: Intended Audience :: Education
Classifier: Operating System :: Microsoft :: Windows :: Windows 10
Classifier: License :: OSI Approved :: MIT License
Classifier: Programming Language :: Python :: 3
Requires-Dist: pandas
Requires-Dist: numpy
Requires-Dist: matplotlib
Requires-Dist: statsmodels
Requires-Dist: keras
Requires-Dist: neuralprophet
Requires-Dist: scikit-learn
Requires-Dist: tqdm
Requires-Dist: tabulate
